src/__init__.py
src/streamer.py
ytstreamer-1.1.4.dist-info/LICENSE
ytstreamer-1.1.4.dist-info/METADATA
ytstreamer-1.1.4.dist-info/WHEEL
ytstreamer-1.1.4.dist-info/entry_points.txt
ytstreamer-1.1.4.dist-info/top_level.txt
ytstreamer-1.1.4.dist-info/RECORD
