Metadata-Version: 2.1
Name: ytstreamer
Version: 1.1.4
Summary: Script that streams music (or audio) from youtube
Home-page: https://github.com/Icelain/YTStreamer
Author: Icelain
Author-email: xerneas965@gmail.com
License: MIT
Keywords: music streaming youtube audio audiostream youtubestream script
Platform: UNKNOWN
Classifier: Programming Language :: Python :: 3
Classifier: License :: OSI Approved :: MIT License
Classifier: Operating System :: OS Independent
Requires-Dist: pafy
Requires-Dist: youtube-dl
Requires-Dist: playsound
Requires-Dist: youtube-data-api
Requires-Dist: pyfiglet
Requires-Dist: colorama
